masosdk/Dataset.py
masosdk/__init__.py
masosdk/config.py
masosdk-0.0.6.dist-info/METADATA
masosdk-0.0.6.dist-info/WHEEL
masosdk-0.0.6.dist-info/top_level.txt
masosdk-0.0.6.dist-info/RECORD
