Metadata-Version: 2.1
Name: masosdk
Version: 0.0.6
Summary: Software Development Kit for Maso
Home-page: https://www.isibrno.cz
Author: Tomas Psorn
Author-email: tomaspsorn@isibrno.cz
License: GPL
Platform: UNKNOWN
Requires-Dist: numpy
Requires-Dist: requests
